RTL/ALU.sv
`timescale 1ns / 1ps
module ALU (
    input logic SignedExt,
    input logic [31:0] A,
    B,
    input logic [2:0] ALUControl,
    output logic [31:0] Y,
    output logic Zero,
    Neg
);

  // ALUControl for basic instructions
  localparam logic [2:0] ADD = 3'b000,
                         SUB = 3'b010,
                         XOR = 3'b100,
                         OR  = 3'b110,
                         AND = 3'b111,
                         SLL = 3'b001,
                         SRL = 3'b101,
                         SRA = 3'b011;

  // logic and arith buses
  logic [31:0] logic_result;
  logic [31:0] arith_result;

  // extended buses
  logic [32:0] A_ext, B_ext;
  logic [32:0] sub_ext;

  assign A_ext[31:0] = A;
  assign B_ext[31:0] = B;

  // extend with or without sign bit
  always_comb begin
    if (SignedExt == 1) begin
      A_ext[32] = A[31];
      B_ext[32] = B[31];
    end else begin
      A_ext[32] = 1'b0;
      B_ext[32] = 1'b0;
    end
  end

  // logic
  always_comb begin
    logic_result = 32'b0;
    case (ALUControl)
      // xor: bit-wise xor
      XOR:  logic_result = A ^ B;
      // or:  bit-wise or
      OR:   logic_result = A | B;
      // and: bit-wise and
      AND:  logic_result = A & B;
      // sll: logical left shift
      SLL:  logic_result = A << B[4:0];
      // srl: logical right shift
      SRL:  logic_result = A >> B[4:0];
      // sra: arithmetic right shift
      SRA:  logic_result = $signed(A) >>> B[4:0];
      default: ;
    endcase
  end

  // arithmetic
  always_comb begin
    arith_result = 32'b0;
    sub_ext = A_ext - B_ext;
    case (ALUControl)
      // add & addi: addition
      ADD:  arith_result = A + B;
      // sub & subi: subtraction
      SUB:  arith_result = sub_ext[31:0];
      default: ;
    endcase
    Neg = sub_ext[32];
  end

  // final mux
  always_comb begin
    case (ALUControl)
      // use arithmetic unit result
      ADD, SUB: Y = arith_result;
      // else use logic unit result
      default: Y = logic_result;
    endcase
    Zero = (Y == 32'b0) ? 1'b1 : 1'b0;
  end

endmodule

ALU/tb_ALU_encripted.sv
`timescale 1ns / 1ps

module tb_ALU;

logic [31:0] A, B;
logic [2:0] ALUControl;
logic [31:0] Y;
logic Zero;

ALU dut (.*);

`pragma protect begin_protected
`pragma protect version=1
`pragma protect encrypt_agent="dvlencrypt"
`pragma protect encrypt_agent_info="Altair Engineering Inc. P1735 encryptor tool"
`pragma protect author="author-a"
`pragma protect author_info="author-a-details"
`pragma protect data_method="aes256-cbc"
`pragma protect key_keyowner="Altair Engineering Inc."
`pragma protect key_keyname="DSim_4k"
`pragma protect key_method="rsa"
`pragma protect key_block
5IkMj2kJBbaM+jX/Ob7sNzTT9RHBVv3zx+4T1fZoBCoa+IHdUlkSffYQS02j7S0E
LnZW24AeBoGlvi0wiyuZv36NSNVjHBQpZ/z7iiMsre7m2jCdUOoduvrGidK7OA4F
58+DnZu8YiwvAuyDK8KLP4LiECf7yD8x/dtZAz0WFZle/0Hm97SlGQO68DcFa6wI
fQe++gAXNJf0zveyNMhLKLOeFSsDnoPV/kh5Hk8YXaO+PFqftTwLOdupKCVNEVu8
RoL72cmzmrDkXAEq9dDvGaiNBjzL52tm0lB36l7MyMeylsD6Ged7s5CbpXNh3EKO
armnAIg1qjDcVDLO1Cy79JiY3S1hS4tX8j/ifHurz8H4Wrr8Jx6fIcSketPt2XDs
df604emNOBCZLbf1EOjCUg/71W6bk7W7Cppz/g7gPHA+EZcwj8I/yO3p4DFAOUiq
jxPi2OjaLpKJFP+gl+CG9Gda55Uw9Rhr8Ghchx74zuammGJDLr441oHpnE/iGgRL
OeoHh2CLkgStMEMdqUDuv73OrlfJxeKaIauT7PzVAIqdPdXvzG9Athjw7PCRiLiJ
k+/0C2yzO13BSR5x7y+JxP1x8aD2lpDm9/BK4zgNvJ1LWdmJA1IsYDJyiATg+UZC
tOSe0/NLp7VCYjeTEYumkTjt/GLhZKjasSoqBH1DRXA=
`pragma protect data_block
re3ijAeJ7fIWt+nQI6ck/uHWK9gJ2NXA7Rog0pW8hUQ+EhaRk5PBY+ObMUIvGgMR
EJYkEdDo2Kpexv/bA5ExxIs6RdJ4F1qHlZxan7ZlI3KsBrl1u0GSWXG98PWtS67v
15VBntLeHHxigw+Xy88JcPw1I/Ytc5d85A8hEile0RLcMMzSWkTbkFyb4RJv240h
w35TgmNgbf5Zo7ufhuzsuZJ1C/dWJ94vo4EXZIENIq2PVfqtyraiSUuFBiTOYuDC
3VfHhCL1nSx7FA+EZAuGy7bhIFkrbwju264RTFmzKhvLM7Uqm6WfmDdigcVomtTR
c+ifi9qvIdDX3bCCc6XXFQ9MFjNbmF7nqHtLTkX3uBTHsCVOL4R5L7y3rj2o7das
ljd9r9Z+n7WfmZyWXvYJDQizeI14SJRSAJ0+404dtdbw9g4bkTAXMJTNv4tP9FoN
lhgjIrXLeowHVCT0d+R8wl3wMjNSFUfnS8OjNmBS8h3MaKypewRo8eVSN14yy5b9
UGLyH8U74knk6+6Iep4XAuDRqLv6vIAMs27+YCEQUPT6WNKK+SvcD1OzGd/cvo5V
aU8V3bXAjm8v2VfnReF8VgVyqnNQoSHVDQGs+dvOkP67YXTTnltC8I7wo2zCT1GU
0PYyv383j0MY3YlTUKUOGP0uFLPdYpxXA0bFdwh07vQKRM+TF662fqtoDeP8DK2b
HHqCBiU/0Na2ypvOfwXQOmjzt51rLexAvgcK5wK1Aa4aIA4GdSX7iDpPsvYdua1e
WcpBGthCtYRZz6xOFvqBPKT+L5y7fKOdD+guWo3zJ4nhztFeUF1wg/AKWdc2FkY0
8+UBr/UYs/SQW8Oy7I0uqRIEcEcqqi3bzcKC7tik2Ir/rPXRNkhI5wbJarKgDDAm
21bruxZgU4EY/5geL9AJ1XB0M1fGLS64qeEGNwzjdBuUAVKzvn8pSeRZWrGVSqWw
n0rMKnOncnSS+dKXRhCVhqCcFZiStTcERVdZ4X2Hial1EUL/H5qzhEps4AsTvHVI
cwTNK5nJrbVBiXiAMvh6Jh6wrBGlfaCa/5p8w/VvsfKRY6PINMuAG1+yO3jKY4wY
XV4UQt5S64/pyYEKlbqpCbAVCNrGlEgCP9woppNAllg15Sfx8ocRssWTbhXVLSoR
1MdjYjAfpU0CPBvQ08ZCGT6lWy5Vnlab1h3192T2c2jgYzIXoi14oNAKigujhZhu
5YMzbkIuxNpGix1Nc8PePJFCfAdgnSQ5dgCW5uI85lGQjqhRzagsa4rOFAY/ezly
lY6TKmDuToE4sjSkxDhcTYEKsLWHoYM7b0ahXSaBlhAglOBkFKZAamDwZocPjT+9
mOJ6cX72jRPO20OJlEZp3+2OCUVEWWs74CrlBqim7SSoBo6qji9Bb2nTRS0t09Qf
ngIG5PnzfCL2bzOEotvGiRWo7J1nSuWpK9SOFZ5htidhOXNRsm2EL7MHuae7r9Cg
uiUea54asgq3+VYRJNj97JMywTFY+MRb5SIBPTA8r/4tZ9EEYiFe5vUzSirjVRWf
Q8AnkAsQsszPN0nN0S0579dvpKD8wHyk0EKNiiwqtFAlkfk1nBH42nWDJcchmlkx
M+CPYKkqhl0sHpK32xAq/cT7NqScfRQBx36xHgt71er6mq+tEZCJ0WJw19iaVsyJ
3DaKEVCLDrY+QKioIX8Zmc+fwxCyqtyyUYNj64I9BMejCzumMzsZWsHK+rXfsm3m
j5tAHfT7mlBk8lFuv9jcf+SFvwhiXgodhqNQEG1yh+BRVghDMb3cEpn4yGXgI/te
qWOmkF4xWJ+Vn0PLOHTQvhRd0B502mAwnMbwaP55mpQ453FORs4K0yj/wDNF3NGC
YA0t/riIyYl7YMwQZp3cNZLkoPf8+NVlCFtFVl3ksj3kvF2jZQijd+ebDHRyr9Gn
y/ABOth/gRDwo2daIHj05rrB2z/g1sgdj3ptO8dfDXQrKWM82h7tDWuKEISnkOUJ
N4wme38b76owCZ1D02VzTf8dHvvJXAxlmy3vmdz3WFGMRSPf+sqaWOuFDoor8Xfk
kegfdMb0dSUZllfLLyF+YTuzRW01ZGB2rAZ+2TfvmpCKUSR52eqJIDy23oKrZ0rs
SPB08+/EFimYSnbseys7ywky1Dim0DGtAHhGnhNmD66iIG1+oV4WxCBO+ENoVgeJ
Lhmb0zcZHPuXcv1SwnEPPm2eAQ5mTbvVyI1rG4H8pZsWHss0W11GZBGajfjdxEKE
ZNUIE7PKbWaIpRRGi7B5Eqsuy6zP4pzj0Fmn1ae4n27Jgs8WlG8ax7OqBCV1NMOS
rOSiFYC0HTfrqpHmv49uNyl1wIze9GLk89Maqo6WEuLHeJfTSN0KHfwIqN0iDC88
0188n1AX9qG6+pYdGjrJqlNVdtMLqn1l0nlAYTQ0uhpX1X67EocMNmJrmt/9wstC
KamOvLIySNUdixupBJ+/YjhCatjp3Pi2UxuuuGYPkt8=
`pragma protect end_protected



endmodule

ALU/dati.vcd
$date May 20, 2026 11:50:57
$end
$version DSim 2026
$end
$timescale 1 ps $end
$scope module $pkgs $end
$scope module std $end
$scope function randomize $end
$upscope $end
$upscope $end
$upscope $end
$scope module tb_ALU $end
$scope module dut $end
$var wire 32 ' A [31:0] $end
$var wire 3 ) ALUControl [2:0] $end
$var wire 32 ( B [31:0] $end
$var reg 32 % Y [31:0] $end
$var reg 1 & Zero  $end
$var reg 32 + arith_result [31:0] $end
$var reg 32 * logic_result [31:0] $end
$upscope $end
$var reg 32 " A [31:0] $end
$var reg 3 $ ALUControl [2:0] $end
$var reg 32 # B [31:0] $end
$var reg 32 % Y [31:0] $end
$var reg 1 & Zero  $end
$upscope $end
$enddefinitions $end
#0
$dumpvars
bx '
bx )
bx (
bx %
x&
bx +
bx *
bx "
bx $
bx #
bx %
x&
$end
b0 $
b01001001 "
b0101011 #
b01001001 '
b0101011 (
b0 )
b0 *
b0 +
b01110100 +
b01110100 %
0&
#1000
b11111111111111111111111101101011 #
b11111111111111111111111101101011 (
b0 +
b11111111111111111111111110110100 +
b11111111111111111111111110110100 %
#2000
b010 $
b010000001 "
b01010001 #
b010 )
b010000001 '
b01010001 (
b0 +
b0110000 +
b0110000 %
#3000
b11111111111111111111111111010111 "
b11111111111111111111111110011111 #
b11111111111111111111111111010111 '
b11111111111111111111111110011111 (
b0 +
b0111000 +
b0111000 %
#4000
b011000110 "
b011000110 #
b011000110 '
b011000110 (
b0 +
b0 %
1&
#5000
b011000101 "
b011000101 '
b11111111111111111111111111111111 +
b11111111111111111111111111111111 %
0&
#6000
b011000110 "
b011000101 #
b011000110 '
b011000101 (
b0 +
b01 +
b01 %
#7000
b01111000011110000111100001010 "
b01111010011110000111100000101 #
b100 $
b01111000011110000111100001010 '
b01111010011110000111100000101 (
b100 )
b010000000000000000001111 *
b0 +
b010000000000000000001111 %
#8000
b110 $
b110 )
b0 *
b01111010011110000111100001111 *
b01111010011110000111100001111 %
#9000
b111 $
b111 )
b0 *
b01111000011110000111100000000 *
b01111000011110000111100000000 %
